{"data":{"site":{"siteMetadata":{"title":"彼岸花开开彼岸","author":"lanxxg"}},"markdownRemark":{"id":"2d34a39e-aedb-5e85-8527-0c21b173eb5e","excerpt":"ESLintPrettierEditorconfig","html":"<h2>ESLint</h2>\n<h2>Prettier</h2>\n<h2>Editorconfig</h2>","frontmatter":{"title":"代码风格指南","date":"August 20, 2019","description":"eslint, prettier and editorconfig."}}},"pageContext":{"isCreatedByStatefulCreatePages":false,"slug":"/how-to-setup-eslint-prettier-editorconfig/","previous":{"fields":{"slug":"/authority-management/"},"frontmatter":{"title":"前端与服务端权限交互设计"}},"next":null}}